gfiberspeedtest/__init__.py
gfiberspeedtest/speedtest_cli.py
gfiberspeedtest-1.0.1.data/scripts/__init__.py
gfiberspeedtest-1.0.1.dist-info/DESCRIPTION.rst
gfiberspeedtest-1.0.1.dist-info/METADATA
gfiberspeedtest-1.0.1.dist-info/RECORD
gfiberspeedtest-1.0.1.dist-info/WHEEL
gfiberspeedtest-1.0.1.dist-info/metadata.json
gfiberspeedtest-1.0.1.dist-info/top_level.txt
